{
	"dir": "h-rider-haggard/she",
	"title": "She",
	"creator": "H. Rider Haggard",
	"description": "Three men travel to Africa and encounter a 2000-year old woman.",
	"version": "v3.3.1",
	"createdAt": "2022-10-04",
	"updatedAt": "2022-10-10",
	"analysis": {
		"wordsCount": 52178,
		"uniqueWordsCount": 5757,
		"ranks": {
			"highest": 50676,
			"lowest": 1
		},
		"levels": {
			"A1": {
				"count": 495,
				"readability": 55
			},
			"A2": {
				"count": 467,
				"readability": 67
			},
			"B1": {
				"count": 857,
				"readability": 80
			},
			"B2": {
				"count": 1273,
				"readability": 89
			},
			"C1": {
				"count": 1280,
				"readability": 96
			},
			"C2": {
				"count": 970,
				"readability": 99
			}
		}
	}
}