{"mrs":323,"yes":254,"good":235,"go":161,"all":150,"look":138,"come":135,"think":135,"say":123,"miss":119,"see":109,"know":107,"now":105,"must":96,"dear":95,"out":93,"about":90,"much":88,"room":84,"one":84,"take":77,"be":76,"tell":76,"little":73,"door":69,"make":67,"may":66,"up":65,"hand":64,"judge":62,"thing":60,"time":60,"table":56,"home":53,"hear":52,"aunt":52,"again":51,"fancy":51,"very":49,"quite":49,"back":48,"just":48,"course":48,"mean":48,"george":47,"after":46,"leave":46,"nothing":45,"write":45,"thea":44,"get":42,"really":42,"long":42,"last":41,"sit":40,"even":40,"book":40,"right":40,"let":39,"never":39,"over":38,"give":38,"some":38,"way":38,"such":38,"hall":37,"sort":37,"thank":36,"two":36,"perhaps":35,"glass":33,"day":33,"put":32,"before":32,"life":32,"find":32,"call":32,"same":31,"other":31,"smile":31,"new":31,"indeed":30,"first":30,"down":29,"letter":29,"manuscript":29,"suppose":29,"mr":29,"rise":28,"through":28,"use":28,"draw":27,"understand":27,"morning":26,"old":26,"inner":26,"heaven":26,"like":26,"pistol":26,"part":25,"seem":25,"stand":24,"poor":24,"happen":24,"work":24,"talk":24,"ibsen":24,"chair":23,"laugh":23,"almost":23,"keep":23,"place":23,"man":23,"play":23,"turn":22,"sofa":22,"yet":22,"town":22,"night":22,"sure":22,"want":22,"lie":21,"softly":21,"well":21,"moment":21,"hair":21,"open":20,"enter":20,"end":20,"house":20,"lay":19,"try":19,"lady":19,"act":18,"stave":18,"appear":18,"ask":18,"seat":18,"rather":18,"point":18,"live":18,"burn":17,"dress":17,"case":17,"read":17,"early":17,"doubt":17,"feel":17,"hat":17,"goodbye":17,"head":17,"shoot":17,"do":17,"bonnet":17,"close":16,"late":16,"remain":16,"together":16,"always":16,"between":16,"people":16,"young":16,"curtain":15,"middle":15,"doorway":15,"speak":15,"believe":15,"care":15,"show":15,"far":15,"word":15,"own":15,"child":15,"god":14,"soon":14,"already":14,"enough":14,"remember":14,"eye":14,"either":14,"vine":14,"husband":14,"still":14,"rest":14,"name":14,"pocket":14,"whole":14,"return":14,"character":14,"sake":13,"paper":13,"packet":13,"friend":13,"matt":13,"alone":13,"away":13,"year":13,"love":13,"great":13,"question":13,"both":13,"carry":13,"auntie":13,"half":12,"bring":12,"wait":12,"party":12,"mind":12,"hope":12,"meet":12,"tear":12,"world":12,"future":12,"deal":12,"sleep":11,"whisper":11,"trouble":11,"piece":11,"begin":11,"near":11,"rate":11,"dare":11,"possible":11,"run":11,"nod":11,"every":11,"subject":11,"mistress":11,"wife":11,"arm":11,"glance":11,"many":11,"please":11,"lamp":10,"listen":10,"ma'am":10,"clear":10,"short":10,"woman":10,"account":10,"behind":10,"side":10,"kind":10,"true":10,"power":10,"light":10,"another":10,"afternoon":10,"present":10,"armchair":9,"hold":9,"servant":9,"certain":9,"watch":9,"promise":9,"presently":9,"stop":9,"front":9,"steal":9,"ever":9,"help":9,"yesterday":9,"three":9,"wish":9,"reason":9,"somewhat":9,"though":9,"throw":9,"corner":9,"boy":9,"follow":9,"exactly":9,"start":9,"fact":9,"pass":9,"different":9,"publish":9,"brandes":9,"receive":9,"bouquet":9,"delight":9,"often":9,"also":8,"fire":8,"quickly":8,"bless":8,"address":8,"able":8,"arrange":8,"truth":8,"parcel":8,"lose":8,"lively":8,"police":8,"change":8,"tone":8,"scarcely":8,"voice":8,"bow":8,"utterly":8,"wrong":8,"breast":8,"piano":8,"each":8,"cold":8,"impossible":8,"answer":8,"manage":8,"figure":8,"ago":8,"set":8,"stupid":8,"large":7,"guess":7,"gentleman":7,"till":7,"affair":7,"meantime":7,"courage":7,"air":7,"declare":7,"surely":7,"fellow":7,"imagine":7,"idea":7,"death":7,"move":7,"assure":7,"unfortunately":7,"mademoiselle":7,"entirely":7,"self":7,"walk":7,"small":7,"cover":7,"news":7,"afraid":7,"forget":7,"lean":7,"happy":7,"forward":7,"specialist":7,"several":7,"christiania":7,"friendship":7,"master":7,"sheriff":7,"marry":7,"face":7,"heart":7,"lovely":7,"comrade":7,"wrap":6,"pause":6,"suddenly":6,"daylight":6,"putt":6,"tire":6,"approach":6,"especially":6,"hour":6,"footstool":6,"finish":6,"pleasure":6,"break":6,"hurry":6,"afterwards":6,"jump":6,"around":6,"creature":6,"story":6,"special":6,"general":6,"fortunately":6,"learn":6,"straight":6,"real":6,"control":6,"respect":6,"happiness":6,"kill":6,"fill":6,"month":6,"fall":6,"dream":6,"nevertheless":6,"under":6,"black":6,"dark":6,"today":6,"bear":6,"terrible":6,"probably":6,"sense":6,"hard":6,"villa":6,"december":6,"flower":6,"suggest":6,"munich":6,"history":6,"summer":6,"experience":6,"five":6,"trait":6,"portrait":6,"wear":6,"shake":6,"travel":6,"slipper":6,"slight":6,"punch":6,"album":6,"foot":5,"sink":5,"eagerly":5,"girl":5,"lord":5,"person":5,"pretty":5,"mortally":5,"press":5,"arrive":5,"fresh":5,"strange":5,"drop":5,"depend":5,"prepare":5,"suppress":5,"overcoat":5,"rush":5,"particularly":5,"curious":5,"become":5,"principle":5,"circle":5,"precisely":5,"however":5,"family":5,"force":5,"garden":5,"exchange":5,"notice":5,"belong":5,"confide":5,"none":5,"hang":5,"beautiful":5,"someone":5,"nice":5,"certainly":5,"wonder":5,"definite":5,"hospital":5,"mortal":5,"curtly":5,"beauty":5,"hush":5,"need":5,"quiet":5,"empty":5,"berlin":5,"original":5,"marriage":5,"poet":5,"october":5,"human":5,"interest":5,"suit":5,"production":5,"london":5,"habit":5,"model":5,"fit":5,"handsome":5,"wall":5,"round":5,"age":5,"wed":5,"tour":5,"journey":5,"expectation":5,"delightful":5,"nonsense":5,"allow":5,"expect":5,"te":5,"vocation":5,"shade":4,"wearily":4,"slip":4,"wood":4,"shut":4,"o'clock":4,"wring":4,"ring":4,"bite":4,"next":4,"sound":4,"enjoy":4,"agree":4,"soul":4,"coffee":4,"despair":4,"searchingly":4,"lightly":4,"possibly":4,"glove":4,"invalid":4,"somewhere":4,"frankly":4,"invite":4,"diana":4,"red":4,"indifferent":4,"court":4,"full":4,"intend":4,"plenty":4,"mine":4,"free":4,"simply":4,"aim":4,"slowly":4,"dangerous":4,"serious":4,"lodging":4,"odd":4,"dreadfully":4,"anxiously":4,"suspense":4,"shriek":4,"drift":4,"deep":4,"destroy":4,"beautifully":4,"few":4,"settee":4,"sister":4,"send":4,"card":4,"die":4,"continue":4,"uneasily":4,"uneasy":4,"line":4,"terror":4,"property":4,"clasp":4,"bed":4,"madam":4,"shoulder":4,"admit":4,"absolutely":4,"search":4,"note":4,"crosse":4,"fashion":4,"conceal":4,"event":4,"difference":4,"demand":4,"touch":4,"gently":4,"bend":4,"scandal":4,"threaten":4,"company":4,"performance":4,"civilisation":4,"de":4,"form":4,"thus":4,"tyrol":4,"engage":4,"week":4,"social":4,"poem":4,"contain":4,"visit":4,"page":4,"second":4,"secretary":4,"type":4,"study":4,"floor":4,"term":4,"photograph":4,"professor":4,"thick":4,"parasol":4,"train":4,"doctor":4,"fair":4,"money":4,"easy":4,"expensive":4,"plan":4,"interrupt":4,"cross":4,"raise":4,"appointment":4,"supper":4,"ten":4,"footrest":3,"broad":3,"loud":3,"waken":3,"stretch":3,"past":3,"seven":3,"spare":3,"alarm":3,"ready":3,"anxious":3,"conceive":3,"horrid":3,"describe":3,"speech":3,"honour":3,"inspire":3,"coat":3,"state":3,"disappear":3,"copy":3,"inspiration":3,"bookcase":3,"detain":3,"clothe":3,"adventure":3,"appearance":3,"decline":3,"violent":3,"firm":3,"select":3,"admirer":3,"haired":3,"scene":3,"march":3,"gaze":3,"movement":3,"single":3,"personage":3,"triangle":3,"cock":3,"basket":3,"exceedingly":3,"glad":3,"ball":3,"peep":3,"content":3,"drawer":3,"irritate":3,"regain":3,"pray":3,"stay":3,"beg":3,"involuntarily":3,"aloud":3,"share":3,"fjord":3,"murder":3,"darkness":3,"perfectly":3,"brave":3,"destiny":3,"father":3,"mother":3,"pure":3,"step":3,"recognise":3,"sheet":3,"iv":3,"mourn":3,"grave":3,"thought":3,"burden":3,"praise":3,"terribly":3,"desperation":3,"joy":3,"impatiently":3,"clench":3,"absurdity":3,"usual":3,"seize":3,"clearly":3,"mix":3,"silence":3,"doubtfully":3,"six":3,"deed":3,"worth":3,"brood":3,"low":3,"freedom":3,"fear":3,"expression":3,"explanation":3,"music":3,"sweet":3,"order":3,"explain":3,"trust":3,"dance":3,"borrow":3,"research":3,"english":3,"count":3,"intention":3,"along":3,"circumstance":3,"dramatic":3,"complete":3,"november":3,"copenhagen":3,"emotion":3,"mood":3,"fraulein":3,"autumn":3,"record":3,"allusion":3,"relation":3,"forever":3,"september":3,"outline":3,"theater":3,"norwegian":3,"theatre":3,"repeat":3,"fine":3,"lecture":3,"numb":3,"thoroughly":3,"grant":3,"difficulty":3,"paint":3,"particular":3,"excite":3,"incident":3,"bottle":3,"lunch":3,"image":3,"ii":3,"society":3,"criticism":3,"genius":3,"represent":3,"indispensable":3,"judgment":3,"colour":3,"rich":3,"detail":3,"common":3,"moral":3,"ruin":3,"cost":3,"high":3,"struggle":3,"lead":3,"outside":3,"grey":3,"accustom":3,"pier":3,"portmanteau":3,"warmly":3,"goodness":3,"pat":3,"cheek":3,"chat":3,"except":3,"library":3,"besides":3,"security":3,"annuity":3,"mere":3,"soft":3,"ill":3,"restless":3,"nervously":3,"concern":3,"post":3,"sensation":3,"imploringly":3,"confidential":3,"suspect":3,"lesson":3,"otherwise":3,"scorn":3,"load":3,"cut":3,"unseen":3,"bore":3,"everlastingly":3,"accept":3,"offer":3,"join":3,"conversation":3,"responsibility":3,"cup":3,"tea":3,"tray":3,"comradeship":3,"roundabout":3,"iii":2,"nearly":2,"smoke":2,"sigh":2,"four":2,"save":2,"incline":2,"rely":2,"fetch":2,"remarkable":2,"confession":2,"breath":2,"ashamed":2,"street":2,"jolly":2,"dye":2,"haste":2,"loathe":2,"bird":2,"critical":2,"track":2,"guest":2,"unmentionable":2,"animate":2,"invitation":2,"alter":2,"purpose":2,"leisure":2,"moreover":2,"enthusiastic":2,"pocketbook":2,"frolic":2,"crazy":2,"hit":2,"station":2,"carefully":2,"duty":2,"exploit":2,"confess":2,"painful":2,"superfluous":2,"lower":2,"threat":2,"shortcut":2,"loudly":2,"hastily":2,"lock":2,"confuse":2,"oval":2,"drag":2,"gather":2,"prefer":2,"service":2,"drive":2,"pour":2,"thousand":2,"collect":2,"scatter":2,"wind":2,"fool":2,"heartless":2,"faith":2,"memento":2,"quire":2,"strike":2,"weep":2,"quietly":2,"peace":2,"calm":2,"sew":2,"brain":2,"rejoice":2,"forgive":2,"absolute":2,"brother":2,"coldly":2,"safe":2,"directly":2,"immovable":2,"advise":2,"literally":2,"fast":2,"glee":2,"absurd":2,"cloak":2,"greet":2,"boardinghouse":2,"incredible":2,"rumour":2,"misunderstand":2,"inquiry":2,"sad":2,"unable":2,"anxiety":2,"confusion":2,"shrug":2,"hesitation":2,"temple":2,"evasively":2,"business":2,"terrify":2,"delirium":2,"extraordinary":2,"loose":2,"dictate":2,"collection":2,"memory":2,"excuse":2,"eager":2,"examination":2,"strength":2,"sorry":2,"illusion":2,"voluntarily":2,"motion":2,"ludicrous":2,"disagreeable":2,"feature":2,"leap":2,"object":2,"proceed":2,"determine":2,"owner":2,"frighten":2,"firmly":2,"discover":2,"repulsive":2,"conclusion":2,"danger":2,"slave":2,"endure":2,"involuntary":2,"imitate":2,"distress":2,"evening":2,"flat":2,"within":2,"cry":2,"persona":2,"west":2,"elias":2,"article":2,"bang":2,"poison":2,"christian":2,"scholarship":2,"pronounce":2,"equal":2,"thou":2,"formal":2,"lack":2,"stage":2,"revert":2,"customary":2,"familiar":2,"introduction":2,"spend":2,"draft":2,"prospect":2,"season":2,"french":2,"produce":2,"occupy":2,"nervous":2,"title":2,"regard":2,"daughter":2,"desire":2,"condition":2,"period":2,"builder":2,"winter":2,"dawn":2,"atmosphere":2,"probable":2,"wander":2,"transmute":2,"theme":2,"create":2,"reality":2,"reveal":2,"creation":2,"son":2,"result":2,"translate":2,"england":2,"america":2,"scandinavia":2,"february":2,"norway":2,"rank":2,"robin":2,"vaudeville":2,"actress":2,"recently":2,"introduce":2,"rival":2,"grind":2,"international":2,"city":2,"ninety":2,"electric":2,"modern":2,"capital":2,"critic":2,"sixty":2,"greatly":2,"picture":2,"simple":2,"individual":2,"dinner":2,"twenty":2,"instance":2,"impulse":2,"therefore":2,"knowledge":2,"intellectual":2,"drink":2,"keg":2,"temptation":2,"art":2,"friendly":2,"whatever":2,"root":2,"port":2,"wine":2,"legatee":2,"sum":2,"fantastic":2,"obvious":2,"ideal":2,"mistake":2,"dionysus":2,"peer":2,"personal":2,"attribute":2,"student":2,"shine":2,"development":2,"prosaic":2,"forecast":2,"excursion":2,"neither":2,"unusual":2,"trifle":2,"above":2,"tragedy":2,"enthusiasm":2,"cherish":2,"venture":2,"cowardice":2,"purchase":2,"decorate":2,"wide":2,"style":2,"fold":2,"pane":2,"whatnot":2,"carpet":2,"pleasant":2,"helpless":2,"proper":2,"grand":2,"abroad":2,"grow":2,"furniture":2,"everyday":2,"hum":2,"beard":2,"carriage":2,"box":2,"pick":2,"examine":2,"waste":2,"trip":2,"buy":2,"improvement":2,"shoe":2,"grub":2,"lucky":2,"cast":2,"secure":2,"salary":2,"domestic":2,"industry":2,"distinction":2,"pale":2,"express":2,"brown":2,"abundant":2,"tasteful":2,"welcome":2,"passably":2,"stone":2,"cling":2,"closely":2,"mountain":2,"kiss":2,"accompany":2,"message":2,"solemn":2,"satisfy":2,"aback":2,"school":2,"country":2,"startle":2,"couple":2,"rapidly":2,"hesitatingly":2,"irreproachable":2,"sharp":2,"fond":2,"cosy":2,"kindness":2,"sadly":2,"sympathy":2,"useful":2,"secret":2,"stroke":2,"influence":2,"reclaim":2,"teach":2,"singe":2,"likely":2,"flourish":2,"salutation":2,"tolerably":2,"apt":2,"competition":2,"consideration":2,"sport":2,"win":2,"matter":2,"saddle":2,"horse":2,"meanwhile":2,"darling":2,"elegant":2,"settle":2,"noon":2,"excellent":2,"positively":2,"correctness":2,"ridiculous":2,"intimate":2,"third":2,"gesture":2,"natural":2,"sudden":2,"bottom":2,"agony":2,"pity":2,"thoughtlessness":2,"ministry":2,"fault":2,"wretched":2,"strict":2,"embarrass":2,"continuation":2,"victory":2,"cigarette":2,"group":2,"peak":2,"dolomite":2,"absorb":2,"smilingly":2,"frankness":2,"motive":2,"partly":2,"frank":2,"coward":2,"passionately":2,"hide":2,"fixedly":2,"distraction":2,"health":2,"shawl":1,"fully":1,"blanket":1,"moan":1,"cautiously":1,"erect":1,"rub":1,"yawn":1,"mouth":1,"immediately":1,"jollification":1,"blockhead":1,"stream":1,"bell":1,"button":1,"shiver":1,"rake":1,"ember":1,"kneel":1,"tiptoe":1,"asleep":1,"arrangement":1,"jealous":1,"pitiful":1,"gift":1,"irreclaimable":1,"incapable":1,"moderation":1,"orgy":1,"ramble":1,"phrase":1,"melancholy":1,"minute":1,"wayside":1,"precious":1,"irreplaceable":1,"deplorably":1,"possession":1,"reproduce":1,"repel":1,"sickness":1,"ugliness":1,"bustle":1,"snatch":1,"stool":1,"flurry":1,"hasten":1,"tiresome":1,"ingenuous":1,"comfort":1,"advance":1,"unhappily":1,"spirit":1,"exception":1,"land":1,"singer":1,"mighty":1,"huntress":1,"protector":1,"glory":1,"amicably":1,"tender":1,"blow":1,"accuse":1,"rob":1,"furious":1,"disturbance":1,"scrimmage":1,"prove":1,"costly":1,"resistance":1,"constable":1,"supply":1,"nocturnal":1,"shrewd":1,"suspicion":1,"blind":1,"mark":1,"henceforth":1,"respectable":1,"intrusive":1,"homeless":1,"fight":1,"weapon":1,"command":1,"vanish":1,"equivocally":1,"capable":1,"spontaneously":1,"construct":1,"objection":1,"piquant":1,"practice":1,"tame":1,"poultry":1,"farewell":1,"key":1,"inkstand":1,"greatcoat":1,"pardon":1,"inquiringly":1,"sleepy":1,"henceforward":1,"despairingly":1,"vehement":1,"protest":1,"afresh":1,"agonise":1,"forebode":1,"improbable":1,"lifework":1,"cool":1,"seawater":1,"current":1,"inaudibly":1,"breathe":1,"heavily":1,"irretrievable":1,"taste":1,"anew":1,"finger":1,"treat":1,"heartlessly":1,"untrue":1,"riot":1,"debauchery":1,"devil":1,"clutch":1,"path":1,"lap":1,"chord":1,"sight":1,"ribbon":1,"cap":1,"circumspectly":1,"lift":1,"aside":1,"shortly":1,"veil":1,"forlorn":1,"tidings":1,"peacefully":1,"unspeakable":1,"bid":1,"mournful":1,"dwell":1,"shroud":1,"tomorrow":1,"whirl":1,"sorrow":1,"lonely":1,"occupant":1,"nurse":1,"total":1,"sick":1,"folk":1,"necessity":1,"busy":1,"affect":1,"completely":1,"injury":1,"scream":1,"unlawful":1,"appropriation":1,"unheard":1,"possess":1,"imperceptible":1,"acknowledge":1,"envy":1,"outburst":1,"mingle":1,"shout":1,"irrepressible":1,"overjoy":1,"nobody":1,"downcast":1,"hurriedly":1,"evident":1,"agitation":1,"misfortune":1,"afloat":1,"witness":1,"imperative":1,"restrain":1,"regret":1,"wail":1,"anger":1,"careful":1,"heed":1,"alive":1,"useless":1,"fix":1,"correctly":1,"horrible":1,"rightly":1,"effort":1,"immortalise":1,"bundle":1,"disorder":1,"dedicate":1,"task":1,"owe":1,"undo":1,"grief":1,"release":1,"deliberate":1,"spontaneous":1,"will":1,"banquet":1,"dispel":1,"amiable":1,"idealise":1,"dead":1,"consciousness":1,"boudoir":1,"wildly":1,"discharge":1,"lodge":1,"vital":1,"bowel":1,"curse":1,"breathless":1,"scrap":1,"ruffle":1,"monument":1,"dispiritedly":1,"recollect":1,"succeed":1,"possibility":1,"reply":1,"accidental":1,"push":1,"bodied":1,"beck":1,"abuse":1,"advantage":1,"impetuously":1,"mockingly":1,"generally":1,"inevitable":1,"intonation":1,"wild":1,"tonight":1,"gaily":1,"lifeless":1,"faint":1,"action":1,"volume":1,"assertion":1,"ingenuity":1,"distil":1,"essence":1,"herman":1,"german":1,"magazine":1,"holder":1,"assessor":1,"widow":1,"cabinet":1,"minister":1,"persuade":1,"pronoun":1,"rebuke":1,"underhand":1,"contrary":1,"usage":1,"familiarity":1,"representation":1,"ignore":1,"onward":1,"throughout":1,"proverbial":1,"june":1,"swedish":1,"slow":1,"progress":1,"july":1,"engross":1,"translator":1,"emptiness":1,"separate":1,"exclusion":1,"constant":1,"intercourse":1,"fictitious":1,"correspondent":1,"indicate":1,"personality":1,"problem":1,"principally":1,"depict":1,"being":1,"groundwork":1,"official":1,"correspondence":1,"glimpse":1,"completion":1,"sea":1,"publication":1,"series":1,"vienna":1,"brief":1,"execute":1,"transfer":1,"bright":1,"sadness":1,"nature":1,"germinate":1,"latter":1,"hypothesis":1,"incubation":1,"gaiety":1,"poetic":1,"utilisation":1,"recent":1,"fain":1,"active":1,"repress":1,"imagination":1,"date":1,"fullness":1,"ripen":1,"busily":1,"preparation":1,"lake":1,"daily":1,"bleak":1,"reaction":1,"sentimental":1,"beget":1,"seek":1,"refuge":1,"chill":1,"materialism":1,"ardent":1,"transcendentalism":1,"knock":1,"plane":1,"poetry":1,"proof":1,"simultaneously":1,"theatrical":1,"january":1,"presence":1,"frau":1,"conrad":1,"lessing":1,"constance":1,"august":1,"bald":1,"list":1,"revival":1,"germany":1,"popular":1,"admirable":1,"elizabeth":1,"lea":1,"april":1,"popularisation":1,"province":1,"york":1,"duse":1,"patrick":1,"campbell":1,"australia":1,"frequently":1,"nance":1,"o'neill":1,"russian":1,"madame":1,"nazimova":1,"notable":1,"success":1,"paris":1,"lemaitre":1,"holland":1,"italy":1,"russia":1,"easily":1,"foretell":1,"worldwide":1,"popularity":1,"sufficient":1,"deliberately":1,"european":1,"car":1,"telephone":1,"conspicuous":1,"factor":1,"notably":1,"absent":1,"gallant":1,"swain":1,"escort":1,"characteristic":1,"comedy":1,"extend":1,"modernise":1,"century":1,"avocation":1,"distinctively":1,"environment":1,"subsidiary":1,"national":1,"product":1,"peculiar":1,"allen":1,"nineteen":1,"suffer":1,"commonly":1,"undoubtedly":1,"composite":1,"initial":1,"process":1,"harmonisation":1,"scheme":1,"prototype":1,"anecdotic":1,"composer":1,"rage":1,"jealousy":1,"prolong":1,"absence":1,"symphony":1,"infinitely":1,"merely":1,"dramatisation":1,"raw":1,"material":1,"addict":1,"conquer":1,"vice":1,"mad":1,"whim":1,"mastery":1,"test":1,"birthday":1,"roll":1,"brandy":1,"withdraw":1,"ward":1,"broach":1,"insensible":1,"anecdote":1,"germ":1,"knit":1,"profoundly":1,"unquestionably":1,"danish":1,"astonish":1,"attach":1,"aberration":1,"worship":1,"rationally":1,"profess":1,"conjecture":1,"belle":1,"dame":1,"mystery":1,"consume":1,"rhine":1,"burgundy":1,"carouse":1,"elapse":1,"postal":1,"residuary":1,"mention":1,"instrument":1,"bremen":1,"bequest":1,"meritorious":1,"spinster":1,"generous":1,"considerably":1,"exceed":1,"amount":1,"proffer":1,"inheritance":1,"enable":1,"add":1,"portraiture":1,"bibulous":1,"thereafter":1,"adopt":1,"pseudonym":1,"willingly":1,"err":1,"discretion":1,"precise":1,"vision":1,"symbol":1,"aspect":1,"bacchic":1,"elation":1,"revelry":1,"antique":1,"follower":1,"entwine":1,"sc":1,"festive":1,"garland":1,"brow":1,"emperor":1,"galilean":1,"pt":1,"julian":1,"procession":1,"impersonate":1,"direct":1,"wreath":1,"relate":1,"artist":1,"frequent":1,"rome":1,"festival":1,"reveller":1,"deck":1,"trace":1,"attempt":1,"obscurity":1,"example":1,"resolution":1,"severely":1,"allege":1,"sociology":1,"necessarily":1,"forth":1,"utter":1,"ability":1,"sociologist":1,"idle":1,"sensible":1,"utterance":1,"retort":1,"intelligent":1,"distinguishable":1,"utopianism":1,"statesmanship":1,"enlighten":1,"activity":1,"fortunate":1,"treatment":1,"abstract":1,"despise":1,"ninny":1,"competent":1,"plod":1,"naturally":1,"method":1,"field":1,"average":1,"scholar":1,"dog":1,"unreasonable":1,"improbability":1,"rough":1,"mechanical":1,"niggle":1,"stress":1,"detach":1,"objective":1,"extract":1,"satire":1,"apply":1,"criminology":1,"dictum":1,"fulfil":1,"requirement":1,"heroine":1,"length":1,"scientific":1,"impassivity":1,"insight":1,"brilliant":1,"remark":1,"quote":1,"whimsical":1,"exaggeration":1,"tendency":1,"keenly":1,"relentlessly":1,"solvent":1,"intelligence":1,"combine":1,"morbid":1,"shrink":1,"gross":1,"sensual":1,"languid":1,"petty":1,"ambition":1,"obstruct":1,"baffle":1,"hanker":1,"refrain":1,"malign":1,"egoism":1,"uncontrolled":1,"aid":1,"quick":1,"subtle":1,"intellect":1,"incur":1,"dignity":1,"revolt":1,"charm":1,"squalid":1,"humiliation":1,"contempt":1,"bad":1,"alike":1,"impel":1,"poignant":1,"literature":1,"pressure":1,"conception":1,"adjustment":1,"crowd":1,"tangle":1,"web":1,"weary":1,"gable":1,"gabble":1,"arch":1,"spacious":1,"tastefully":1,"furnish":1,"opposite":1,"verandah":1,"tree":1,"foliage":1,"surround":1,"porcelain":1,"cushion":1,"upper":1,"majolica":1,"ornament":1,"elderly":1,"uniform":1,"opal":1,"vase":1,"sun":1,"comely":1,"nicely":1,"costume":1,"plain":1,"countrified":1,"stir":1,"steamboat":1,"lot":1,"unpack":1,"loss":1,"wrench":1,"ride":1,"road":1,"feather":1,"match":1,"foreign":1,"university":1,"clever":1,"significantly":1,"chintz":1,"abide":1,"size":1,"thirty":1,"stout":1,"cheerful":1,"spectacle":1,"carelessly":1,"comfortable":1,"indoor":1,"spite":1,"safely":1,"pile":1,"attic":1,"chock":1,"document":1,"archive":1,"untie":1,"string":1,"gorgeous":1,"invest":1,"comfortably":1,"awhile":1,"beset":1,"complacently":1,"confidentially":1,"degree":1,"confer":1,"nowadays":1,"afoot":1,"parlour":1,"bedroom":1,"increase":1,"specially":1,"anywhere":1,"market":1,"luck":1,"expense":1,"frightfully":1,"number":1,"favourable":1,"mortgage":1,"pay":1,"sacrifice":1,"smooth":1,"reach":1,"goal":1,"sometimes":1,"marvellous":1,"oppose":1,"bar":1,"misguide":1,"beat":1,"embrace":1,"refinement":1,"complexion":1,"opaque":1,"steel":1,"unruffled":1,"repose":1,"agreeable":1,"gown":1,"hearty":1,"embarrassment":1,"bride":1,"surrounding":1,"veranda":1,"flood":1,"sunshine":1,"stack":1,"newspaper":1,"embroider":1,"association":1,"consternation":1,"mutter":1,"splendid":1,"insist":1,"downwards":1,"preserve":1,"fling":1,"yellow":1,"wither":1,"manner":1,"annoy":1,"pitch":1,"prevail":1,"convenient":1,"flame":1,"hole":1,"fragile":1,"blue":1,"prominent":1,"inquire":1,"remarkably":1,"flaxen":1,"unusually":1,"wavy":1,"midday":1,"tutor":1,"regular":1,"conduct":1,"unsettle":1,"big":1,"fortnight":1,"sell":1,"errand":1,"shop":1,"implore":1,"kindly":1,"branch":1,"science":1,"earnestly":1,"accord":1,"cordial":1,"apprehensively":1,"schoolfellows":1,"class":1,"stair":1,"pull":1,"silly":1,"apart":1,"distinctly":1,"renew":1,"compassionately":1,"helplessly":1,"housekeeper":1,"governess":1,"rarely":1,"housekeep":1,"slap":1,"neighbourhood":1,"district":1,"altogether":1,"irritably":1,"repellent":1,"imperceptibly":1,"twitch":1,"vehemently":1,"clean":1,"flight":1,"openly":1,"aught":1,"gradually":1,"gain":1,"infinity":1,"assistance":1,"gloomily":1,"shadow":1,"wholly":1,"vague":1,"allude":1,"composure":1,"firearm":1,"spring":1,"epistle":1,"gate":1,"forty":1,"build":1,"elastic":1,"roundish":1,"aristocratic":1,"profile":1,"eyebrow":1,"moustache":1,"youthful":1,"eyeglass":1,"actually":1,"impatience":1,"au":1,"mutual":1,"sufficiently":1,"rearrangement":1,"additional":1,"economically":1,"shabby":1,"catch":1,"region":1,"reform":1,"talent":1,"grieve":1,"irretrievably":1,"worry":1,"indifferently":1,"information":1,"wash":1,"defer":1,"hitch":1,"nomination":1,"conditional":1,"competitor":1,"gesticulate":1,"debt":1,"contest":1,"upset":1,"recline":1,"deny":1,"adventurous":1,"compact":1,"hostess":1,"livery":1,"footman":1,"aghast":1,"beam":1,"covert":1,"remove":1,"bookshelf":1,"caller":1,"revolver":1,"distance":1,"sneak":1,"prank":1,"deuce":1,"game":1,"visitor":1,"chink":1,"parley":1,"stupidity":1,"impatient":1,"eternity":1,"parchment":1,"malice":1,"sympathetically":1,"downright":1,"earnest":1,"deprivation":1,"intolerable":1,"assent":1,"undeniable":1,"amuse":1,"sicken":1,"disgust":1,"wonderful":1,"shudder":1,"assuredly":1,"respectability":1,"beyond":1,"untiring":1,"attain":1,"fatigue":1,"hazard":1,"provide":1,"adorer":1,"entertain":1,"tie":1,"institution":1,"jestingly":1,"require":1,"interior":1,"triangular":1,"convenience":1,"railway":1,"tes":1,"passenger":1,"ankle":1,"repulsion":1,"sympathetic":1,"fund":1,"topic":1,"audible":1,"relief":1,"direction":1,"unbind":1,"warm":1,"perspire":1,"soundness":1,"disappointment":1,"everlasting":1,"episode":1,"pretend":1,"resist":1,"legend":1,"writhe":1,"torment":1,"consequence":1,"constitute":1,"bond":1,"engagement":1,"exquisite":1,"rap":1,"homelike":1,"smell":1,"lavender":1,"dry":1,"scent":1,"legacy":1,"odour":1,"mortality":1,"remind":1,"horribly":1,"attract":1,"politic":1,"political":1,"satisfaction":1,"genteel":1,"poverty":1,"pitiable":1,"elsewhere":1,"stimulate":1,"store":1,"toss":1,"annoyance":1,"professorship":1,"language":1,"angrily":1,"warily":1,"hence":1,"unlike":1,"generality":1,"warn":1,"float":1,"dubiously":1,"gird":1,"bachelor":1,"adapt":1,"convert":1,"sinner":1,"slim":1,"blackish":1,"patch":1,"silk":1,"rapid":1,"subdue":1,"slightly":1,"likewise":1,"wise":1,"position":1,"handwriting":1,"section":1,"civilise":1,"drum":1,"replace":1,"mainly":1,"favour":1,"decidedly":1,"interpose":1,"bind":1,"deliver":1,"compete":1,"decanter":1,"approval":1,"thunderstruck":1,"thunderstorm":1,"stirrup":1,"amiss":1,"weight":1,"refusal":1,"range":1,"underneath":1,"practise":1,"indignation":1,"sharply":1,"view":1,"affectionately":1,"biscuit":1,"apparently":1,"offence":1,"unfaithfulness":1,"tempt":1,"fun":1,"village":1,"below":1,"tourist":1,"spark":1,"tinge":1,"fascinate":1,"intimacy":1,"window":1,"illustrate":1,"escapade":1,"devilment":1,"observe":1,"purge":1,"stain":1,"confessor":1,"incomprehensible":1,"forbid":1,"thirst":1,"develop":1,"shame":1,"dread":1,"ample":1,"consolation":1,"cowardly":1,"arrant":1,"beneath":1,"crave":1,"twilight":1,"silent":1,"reseat":1,"perfect":1,"liveable":1,"seriously":1,"confident":1,"joyfully":1,"plainly":1,"contemptuous":1,"approvingly":1,"rock":1,"faithful":1,"caress":1,"surprise":1,"piteously":1,"distort":1,"confidence":1,"lip":1,"husky":1,"hurrah":1,"refill":1,"urge":1,"office":1,"prevent":1,"calmly":1,"angry":1,"radiant":1,"pinch":1,"ms":1,"printer":1,"somehow":1,"thereabouts":1,"liveliness":1,"restlessly":1,"flush":1,"fearless":1,"mould":1,"fate":1,"dine":1,"landmark":1}