{"dir":"samuel-butler/erewhon","title":"Erewhon","creator":"Samuel Butler","description":"A traveller ventures to the unknown country of Erewhon and finds a surprisingly different culture.","version":"v3.2.1","createdAt":"2022-10-04","updatedAt":"2022-10-04","analysis":{"wordsCount":38538,"uniqueWordsCount":5398,"ranks":{"highest":49758,"lowest":1},"levels":{"A1":{"count":466,"readability":56},"A2":{"count":470,"readability":67},"B1":{"count":816,"readability":79},"B2":{"count":1162,"readability":89},"C1":{"count":1202,"readability":95},"C2":{"count":894,"readability":99}}}}